{
  "kind": "collectionType",
  "collectionName": "sponsor_types",
  "info": {
    "singularName": "sponsor-type",
    "pluralName": "sponsor-types",
    "displayName": "Sponsor type",
    "description": ""
  },
  "options": {
    "draftAndPublish": false
  },
  "pluginOptions": {},
  "attributes": {
    "Name": {
      "type": "string",
      "unique": true
    },
    "Order": {
      "type": "integer",
      "default": 0
    },
    "LogoSize": {
      "type": "enumeration",
      "enum": [
        "S",
        "M",
        "L",
        "XL",
        "XXL"
      ],
      "required": true,
      "default": "L"
    },
    "ShowOnHomePage": {
      "type": "boolean",
      "default": true,
      "required": true
    },
    "ShowAudioPlayerFixed": {
      "type": "boolean",
      "default": false,
      "required": true
    },
    "ShowAudioPlayerRotating": {
      "type": "boolean"
    }
  }
}
